ActiveList/__init__.py
active_list_mc-0.6.dist-info/LICENSE
active_list_mc-0.6.dist-info/WHEEL
active_list_mc-0.6.dist-info/METADATA
active_list_mc-0.6.dist-info/RECORD
