Metadata-Version: 2.1
Name: active-list-mc
Version: 0.6
Summary: Facade to simplify usage of Gtk.TreeView
License: MIT
Author: Chris Brown
Author-email: chris@marcrisoft.co.uk
Requires-Python: >=3.8,<4.0
Classifier: Development Status :: 4 - Beta
Classifier: Intended Audience :: End Users/Desktop
Classifier: License :: OSI Approved :: MIT License
Classifier: Programming Language :: Python :: 3
Classifier: Programming Language :: Python :: 3.10
Classifier: Programming Language :: Python :: 3.8
Classifier: Programming Language :: Python :: 3.9
Requires-Dist: PyGObject (>=3.42.0,<4.0.0)
Requires-Dist: tomlkit (<1.0.0)
